azstoragetorch/__init__.py
azstoragetorch/_client.py
azstoragetorch/_version.py
azstoragetorch/datasets.py
azstoragetorch/exceptions.py
azstoragetorch/io.py
azstoragetorch-0.2.0.dist-info/licenses/LICENSE
azstoragetorch-0.2.0.dist-info/METADATA
azstoragetorch-0.2.0.dist-info/WHEEL
azstoragetorch-0.2.0.dist-info/top_level.txt
azstoragetorch-0.2.0.dist-info/RECORD
