Metadata-Version: 2.4
Name: azstoragetorch
Version: 0.2.0
Summary: Azure Storage Connector for PyTorch
Author-email: Microsoft Corporation <ascl@microsoft.com>
License: MIT License
Project-URL: Homepage, https://github.com/Azure/azure-storage-for-pytorch
Project-URL: Issues, https://github.com/Azure/azure-storage-for-pytorch/issues
Project-URL: Repository, https://github.com/Azure/azure-storage-for-pytorch
Keywords: azure,pytorch
Classifier: Development Status :: 4 - Beta
Classifier: License :: OSI Approved :: MIT License
Classifier: Programming Language :: Python
Classifier: Programming Language :: Python :: 3
Classifier: Programming Language :: Python :: 3 :: Only
Classifier: Programming Language :: Python :: 3.10
Classifier: Programming Language :: Python :: 3.11
Classifier: Programming Language :: Python :: 3.12
Classifier: Programming Language :: Python :: 3.13
Classifier: Programming Language :: Python :: 3.14
Requires-Python: >=3.10
License-File: LICENSE
Requires-Dist: azure-identity<2
Requires-Dist: azure-storage-blob<=12.27.0,>=12.24.0
Requires-Dist: torch<3,>=2.6.0
Requires-Dist: typing-extensions<5,>=4.13.2
Provides-Extra: dev
Requires-Dist: build; extra == "dev"
Requires-Dist: check-manifest; extra == "dev"
Requires-Dist: pytest; extra == "dev"
Requires-Dist: sphinx; extra == "dev"
Requires-Dist: furo; extra == "dev"
Requires-Dist: sphinx-copybutton; extra == "dev"
Requires-Dist: ruff; extra == "dev"
Requires-Dist: mypy; extra == "dev"
Requires-Dist: sphinx-design; extra == "dev"
Dynamic: license-file
